underscoreclass/__init__.py
underscoreclass-0.1.0.dist-info/METADATA
underscoreclass-0.1.0.dist-info/WHEEL
underscoreclass-0.1.0.dist-info/top_level.txt
underscoreclass-0.1.0.dist-info/RECORD
