Metadata-Version: 2.1
Name: underscoreclass
Version: 0.1.0
Summary: "(_^o^_)" can now be valid Python syntax.
Home-page: UNKNOWN
Author: Seth Peace
Author-email: sethevanpeace@gmail.com
License: MIT
Platform: UNKNOWN
Classifier: License :: OSI Approved :: MIT License
Classifier: Programming Language :: Python :: 3
Classifier: Programming Language :: Python :: 3.9
